{
  "bookName": "2 Samuel",
  "bookId": 10,
  "sentiment": [
    {"book":"2 Samuel","chapter":1,"exaltation":2,"peace":1,"admonition":4,"contrition":8,"dominant":"contrition","rationale":"David mourns Saul and Jonathan with a deeply sorrowful lament over the fallen heroes of Israel."},
    {"book":"2 Samuel","chapter":2,"exaltation":3,"peace":2,"admonition":6,"contrition":3,"dominant":"admonition","rationale":"Civil war erupts between the house of Saul and the house of David, with the death of Asahel."},
    {"book":"2 Samuel","chapter":3,"exaltation":3,"peace":3,"admonition":7,"contrition":5,"dominant":"admonition","rationale":"Abner defects to David but is murdered by Joab; David mourns Abner and curses Joab's house."},
    {"book":"2 Samuel","chapter":4,"exaltation":1,"peace":1,"admonition":8,"contrition":3,"dominant":"admonition","rationale":"Ish-bosheth is assassinated; David executes the murderers for slaying a righteous man."},
    {"book":"2 Samuel","chapter":5,"exaltation":8,"peace":6,"admonition":0,"contrition":0,"dominant":"exaltation","rationale":"David is anointed king over all Israel, captures Jerusalem, and defeats the Philistines with divine guidance."},
    {"book":"2 Samuel","chapter":6,"exaltation":8,"peace":5,"admonition":3,"contrition":1,"dominant":"exaltation","rationale":"The Ark is brought to Jerusalem with great celebration, though Uzzah is struck and Michal despises David."},
    {"book":"2 Samuel","chapter":7,"exaltation":8,"peace":9,"admonition":0,"contrition":0,"dominant":"peace","rationale":"God establishes the Davidic Covenant through Nathan, and David responds with a humble prayer of gratitude."},
    {"book":"2 Samuel","chapter":8,"exaltation":7,"peace":5,"admonition":0,"contrition":0,"dominant":"exaltation","rationale":"David's military victories over surrounding nations and the expansion of his kingdom under divine favor."},
    {"book":"2 Samuel","chapter":9,"exaltation":2,"peace":8,"admonition":0,"contrition":0,"dominant":"peace","rationale":"David shows covenant kindness to Mephibosheth, Jonathan's son, restoring Saul's land and inviting him to the king's table."},
    {"book":"2 Samuel","chapter":10,"exaltation":4,"peace":1,"admonition":5,"contrition":0,"dominant":"admonition","rationale":"The Ammonites insult David's ambassadors, leading to war and the defeat of Ammon and their Syrian allies."},
    {"book":"2 Samuel","chapter":11,"exaltation":0,"peace":0,"admonition":9,"contrition":3,"dominant":"admonition","rationale":"David commits adultery with Bathsheba and arranges the death of Uriah—a profound moral failure."},
    {"book":"2 Samuel","chapter":12,"exaltation":2,"peace":2,"admonition":8,"contrition":7,"dominant":"admonition","rationale":"Nathan confronts David with the parable of the ewe lamb; the child dies, but Solomon is born."},
    {"book":"2 Samuel","chapter":13,"exaltation":0,"peace":0,"admonition":8,"contrition":7,"dominant":"admonition","rationale":"Amnon violates Tamar, Absalom avenges her by killing Amnon, and flees into exile."},
    {"book":"2 Samuel","chapter":14,"exaltation":1,"peace":3,"admonition":5,"contrition":3,"dominant":"admonition","rationale":"Joab uses the wise woman of Tekoa to persuade David to allow Absalom to return from exile."},
    {"book":"2 Samuel","chapter":15,"exaltation":1,"peace":2,"admonition":6,"contrition":6,"dominant":"contrition","rationale":"Absalom conspires to steal the kingdom; David flees Jerusalem weeping in deep sorrow and humility."},
    {"book":"2 Samuel","chapter":16,"exaltation":0,"peace":1,"admonition":7,"contrition":5,"dominant":"admonition","rationale":"Shimei curses David, Ziba deceives him, and Absalom enters Jerusalem following Ahithophel's counsel."},
    {"book":"2 Samuel","chapter":17,"exaltation":1,"peace":2,"admonition":6,"contrition":2,"dominant":"admonition","rationale":"Hushai overthrows Ahithophel's counsel, saving David; Ahithophel takes his own life."},
    {"book":"2 Samuel","chapter":18,"exaltation":1,"peace":1,"admonition":5,"contrition":8,"dominant":"contrition","rationale":"Absalom is killed by Joab; David's grief-stricken cry for his son is one of scripture's most poignant moments."},
    {"book":"2 Samuel","chapter":19,"exaltation":2,"peace":5,"admonition":3,"contrition":3,"dominant":"peace","rationale":"David returns to Jerusalem, pardons Shimei, and settles disputes among his supporters in a spirit of restoration."},
    {"book":"2 Samuel","chapter":20,"exaltation":1,"peace":2,"admonition":7,"contrition":1,"dominant":"admonition","rationale":"Sheba's rebellion against David is put down by Joab, ending with the wise woman of Abel saving her city."},
    {"book":"2 Samuel","chapter":21,"exaltation":2,"peace":3,"admonition":6,"contrition":4,"dominant":"admonition","rationale":"A famine from Saul's bloodguilt against the Gibeonites is resolved through justice, followed by wars with Philistine giants."},
    {"book":"2 Samuel","chapter":22,"exaltation":10,"peace":7,"admonition":2,"contrition":1,"dominant":"exaltation","rationale":"David's great psalm of deliverance, praising God as his rock, fortress, and deliverer from all enemies."},
    {"book":"2 Samuel","chapter":23,"exaltation":6,"peace":5,"admonition":1,"contrition":0,"dominant":"exaltation","rationale":"David's last words and the roll call of his mighty men and their legendary deeds of valor."},
    {"book":"2 Samuel","chapter":24,"exaltation":2,"peace":4,"admonition":7,"contrition":6,"dominant":"admonition","rationale":"David numbers the people, a plague comes as judgment, and he purchases Araunah's threshingfloor for sacrifice."}
  ],
  "speakers": [
    {"book":"2 Samuel","chapter":1,"startVerse":3,"endVerse":4,"speaker":"David"},
    {"book":"2 Samuel","chapter":1,"startVerse":5,"endVerse":5,"speaker":"David"},
    {"book":"2 Samuel","chapter":1,"startVerse":8,"endVerse":8,"speaker":"David"},
    {"book":"2 Samuel","chapter":1,"startVerse":14,"endVerse":16,"speaker":"David"},
    {"book":"2 Samuel","chapter":1,"startVerse":19,"endVerse":27,"speaker":"David"},
    {"book":"2 Samuel","chapter":2,"startVerse":1,"endVerse":1,"speaker":"David"},
    {"book":"2 Samuel","chapter":2,"startVerse":1,"endVerse":1,"speaker":"Jesus Christ"},
    {"book":"2 Samuel","chapter":2,"startVerse":4,"endVerse":6,"speaker":"David"},
    {"book":"2 Samuel","chapter":2,"startVerse":20,"endVerse":21,"speaker":"Abner"},
    {"book":"2 Samuel","chapter":2,"startVerse":21,"endVerse":21,"speaker":"Asahel"},
    {"book":"2 Samuel","chapter":2,"startVerse":22,"endVerse":22,"speaker":"Abner"},
    {"book":"2 Samuel","chapter":2,"startVerse":26,"endVerse":26,"speaker":"Abner"},
    {"book":"2 Samuel","chapter":2,"startVerse":27,"endVerse":27,"speaker":"Joab"},
    {"book":"2 Samuel","chapter":3,"startVerse":7,"endVerse":7,"speaker":"Ish-bosheth"},
    {"book":"2 Samuel","chapter":3,"startVerse":8,"endVerse":8,"speaker":"Abner"},
    {"book":"2 Samuel","chapter":3,"startVerse":12,"endVerse":12,"speaker":"Abner"},
    {"book":"2 Samuel","chapter":3,"startVerse":13,"endVerse":13,"speaker":"David"},
    {"book":"2 Samuel","chapter":3,"startVerse":14,"endVerse":14,"speaker":"David"},
    {"book":"2 Samuel","chapter":3,"startVerse":16,"endVerse":16,"speaker":"Abner"},
    {"book":"2 Samuel","chapter":3,"startVerse":17,"endVerse":18,"speaker":"Abner"},
    {"book":"2 Samuel","chapter":3,"startVerse":21,"endVerse":21,"speaker":"Abner"},
    {"book":"2 Samuel","chapter":3,"startVerse":24,"endVerse":25,"speaker":"Joab"},
    {"book":"2 Samuel","chapter":3,"startVerse":28,"endVerse":29,"speaker":"David"},
    {"book":"2 Samuel","chapter":3,"startVerse":31,"endVerse":31,"speaker":"David"},
    {"book":"2 Samuel","chapter":3,"startVerse":33,"endVerse":34,"speaker":"David"},
    {"book":"2 Samuel","chapter":3,"startVerse":38,"endVerse":39,"speaker":"David"},
    {"book":"2 Samuel","chapter":4,"startVerse":9,"endVerse":12,"speaker":"David"},
    {"book":"2 Samuel","chapter":5,"startVerse":2,"endVerse":2,"speaker":"Jesus Christ"},
    {"book":"2 Samuel","chapter":5,"startVerse":6,"endVerse":6,"speaker":"David"},
    {"book":"2 Samuel","chapter":5,"startVerse":8,"endVerse":8,"speaker":"David"},
    {"book":"2 Samuel","chapter":5,"startVerse":19,"endVerse":19,"speaker":"Jesus Christ"},
    {"book":"2 Samuel","chapter":5,"startVerse":20,"endVerse":20,"speaker":"David"},
    {"book":"2 Samuel","chapter":5,"startVerse":23,"endVerse":24,"speaker":"Jesus Christ"},
    {"book":"2 Samuel","chapter":6,"startVerse":9,"endVerse":9,"speaker":"David"},
    {"book":"2 Samuel","chapter":6,"startVerse":20,"endVerse":20,"speaker":"Michal"},
    {"book":"2 Samuel","chapter":6,"startVerse":21,"endVerse":22,"speaker":"David"},
    {"book":"2 Samuel","chapter":7,"startVerse":2,"endVerse":2,"speaker":"David"},
    {"book":"2 Samuel","chapter":7,"startVerse":3,"endVerse":3,"speaker":"Nathan"},
    {"book":"2 Samuel","chapter":7,"startVerse":5,"endVerse":16,"speaker":"Nathan"},
    {"book":"2 Samuel","chapter":7,"startVerse":18,"endVerse":29,"speaker":"David"},
    {"book":"2 Samuel","chapter":9,"startVerse":1,"endVerse":1,"speaker":"David"},
    {"book":"2 Samuel","chapter":9,"startVerse":2,"endVerse":2,"speaker":"Ziba"},
    {"book":"2 Samuel","chapter":9,"startVerse":3,"endVerse":3,"speaker":"David"},
    {"book":"2 Samuel","chapter":9,"startVerse":3,"endVerse":3,"speaker":"Ziba"},
    {"book":"2 Samuel","chapter":9,"startVerse":4,"endVerse":4,"speaker":"Ziba"},
    {"book":"2 Samuel","chapter":9,"startVerse":6,"endVerse":6,"speaker":"Mephibosheth"},
    {"book":"2 Samuel","chapter":9,"startVerse":7,"endVerse":7,"speaker":"David"},
    {"book":"2 Samuel","chapter":9,"startVerse":8,"endVerse":8,"speaker":"Mephibosheth"},
    {"book":"2 Samuel","chapter":9,"startVerse":9,"endVerse":10,"speaker":"David"},
    {"book":"2 Samuel","chapter":9,"startVerse":11,"endVerse":11,"speaker":"Ziba"},
    {"book":"2 Samuel","chapter":10,"startVerse":2,"endVerse":2,"speaker":"David"},
    {"book":"2 Samuel","chapter":10,"startVerse":11,"endVerse":12,"speaker":"Joab"},
    {"book":"2 Samuel","chapter":11,"startVerse":3,"endVerse":3,"speaker":"Bathsheba"},
    {"book":"2 Samuel","chapter":11,"startVerse":6,"endVerse":6,"speaker":"David"},
    {"book":"2 Samuel","chapter":11,"startVerse":8,"endVerse":8,"speaker":"David"},
    {"book":"2 Samuel","chapter":11,"startVerse":10,"endVerse":10,"speaker":"Uriah"},
    {"book":"2 Samuel","chapter":11,"startVerse":11,"endVerse":11,"speaker":"Uriah"},
    {"book":"2 Samuel","chapter":11,"startVerse":12,"endVerse":12,"speaker":"David"},
    {"book":"2 Samuel","chapter":11,"startVerse":15,"endVerse":15,"speaker":"David"},
    {"book":"2 Samuel","chapter":11,"startVerse":25,"endVerse":25,"speaker":"David"},
    {"book":"2 Samuel","chapter":12,"startVerse":1,"endVerse":4,"speaker":"Nathan"},
    {"book":"2 Samuel","chapter":12,"startVerse":5,"endVerse":6,"speaker":"David"},
    {"book":"2 Samuel","chapter":12,"startVerse":7,"endVerse":12,"speaker":"Nathan"},
    {"book":"2 Samuel","chapter":12,"startVerse":13,"endVerse":13,"speaker":"David"},
    {"book":"2 Samuel","chapter":12,"startVerse":13,"endVerse":13,"speaker":"Nathan"},
    {"book":"2 Samuel","chapter":12,"startVerse":22,"endVerse":23,"speaker":"David"},
    {"book":"2 Samuel","chapter":13,"startVerse":4,"endVerse":4,"speaker":"Jonadab"},
    {"book":"2 Samuel","chapter":13,"startVerse":5,"endVerse":5,"speaker":"Jonadab"},
    {"book":"2 Samuel","chapter":13,"startVerse":6,"endVerse":6,"speaker":"Amnon"},
    {"book":"2 Samuel","chapter":13,"startVerse":9,"endVerse":9,"speaker":"Amnon"},
    {"book":"2 Samuel","chapter":13,"startVerse":10,"endVerse":10,"speaker":"Amnon"},
    {"book":"2 Samuel","chapter":13,"startVerse":11,"endVerse":11,"speaker":"Amnon"},
    {"book":"2 Samuel","chapter":13,"startVerse":12,"endVerse":13,"speaker":"Tamar"},
    {"book":"2 Samuel","chapter":13,"startVerse":15,"endVerse":15,"speaker":"Amnon"},
    {"book":"2 Samuel","chapter":13,"startVerse":16,"endVerse":16,"speaker":"Tamar"},
    {"book":"2 Samuel","chapter":13,"startVerse":17,"endVerse":17,"speaker":"Amnon"},
    {"book":"2 Samuel","chapter":13,"startVerse":20,"endVerse":20,"speaker":"Absalom"},
    {"book":"2 Samuel","chapter":13,"startVerse":25,"endVerse":25,"speaker":"Absalom"},
    {"book":"2 Samuel","chapter":13,"startVerse":26,"endVerse":26,"speaker":"Absalom"},
    {"book":"2 Samuel","chapter":13,"startVerse":28,"endVerse":29,"speaker":"Absalom"},
    {"book":"2 Samuel","chapter":13,"startVerse":32,"endVerse":33,"speaker":"Jonadab"},
    {"book":"2 Samuel","chapter":14,"startVerse":4,"endVerse":7,"speaker":"Joab"},
    {"book":"2 Samuel","chapter":14,"startVerse":8,"endVerse":8,"speaker":"David"},
    {"book":"2 Samuel","chapter":14,"startVerse":10,"endVerse":10,"speaker":"David"},
    {"book":"2 Samuel","chapter":14,"startVerse":11,"endVerse":11,"speaker":"David"},
    {"book":"2 Samuel","chapter":14,"startVerse":19,"endVerse":19,"speaker":"David"},
    {"book":"2 Samuel","chapter":14,"startVerse":21,"endVerse":21,"speaker":"David"},
    {"book":"2 Samuel","chapter":14,"startVerse":24,"endVerse":24,"speaker":"David"},
    {"book":"2 Samuel","chapter":14,"startVerse":30,"endVerse":30,"speaker":"Absalom"},
    {"book":"2 Samuel","chapter":14,"startVerse":32,"endVerse":32,"speaker":"Absalom"},
    {"book":"2 Samuel","chapter":15,"startVerse":2,"endVerse":4,"speaker":"Absalom"},
    {"book":"2 Samuel","chapter":15,"startVerse":7,"endVerse":8,"speaker":"Absalom"},
    {"book":"2 Samuel","chapter":15,"startVerse":9,"endVerse":9,"speaker":"David"},
    {"book":"2 Samuel","chapter":15,"startVerse":14,"endVerse":14,"speaker":"David"},
    {"book":"2 Samuel","chapter":15,"startVerse":19,"endVerse":20,"speaker":"David"},
    {"book":"2 Samuel","chapter":15,"startVerse":21,"endVerse":21,"speaker":"Ittai"},
    {"book":"2 Samuel","chapter":15,"startVerse":22,"endVerse":22,"speaker":"David"},
    {"book":"2 Samuel","chapter":15,"startVerse":25,"endVerse":26,"speaker":"David"},
    {"book":"2 Samuel","chapter":15,"startVerse":33,"endVerse":34,"speaker":"David"},
    {"book":"2 Samuel","chapter":15,"startVerse":35,"endVerse":36,"speaker":"David"},
    {"book":"2 Samuel","chapter":16,"startVerse":2,"endVerse":2,"speaker":"Ziba"},
    {"book":"2 Samuel","chapter":16,"startVerse":3,"endVerse":3,"speaker":"David"},
    {"book":"2 Samuel","chapter":16,"startVerse":3,"endVerse":3,"speaker":"Ziba"},
    {"book":"2 Samuel","chapter":16,"startVerse":4,"endVerse":4,"speaker":"David"},
    {"book":"2 Samuel","chapter":16,"startVerse":9,"endVerse":9,"speaker":"Abishai"},
    {"book":"2 Samuel","chapter":16,"startVerse":10,"endVerse":12,"speaker":"David"},
    {"book":"2 Samuel","chapter":16,"startVerse":20,"endVerse":20,"speaker":"Absalom"},
    {"book":"2 Samuel","chapter":16,"startVerse":21,"endVerse":21,"speaker":"Ahithophel"},
    {"book":"2 Samuel","chapter":17,"startVerse":1,"endVerse":3,"speaker":"Ahithophel"},
    {"book":"2 Samuel","chapter":17,"startVerse":5,"endVerse":5,"speaker":"Absalom"},
    {"book":"2 Samuel","chapter":17,"startVerse":7,"endVerse":13,"speaker":"Hushai"},
    {"book":"2 Samuel","chapter":17,"startVerse":15,"endVerse":16,"speaker":"Hushai"},
    {"book":"2 Samuel","chapter":17,"startVerse":21,"endVerse":21,"speaker":"Ahimaaz"},
    {"book":"2 Samuel","chapter":18,"startVerse":2,"endVerse":2,"speaker":"David"},
    {"book":"2 Samuel","chapter":18,"startVerse":3,"endVerse":3,"speaker":"David"},
    {"book":"2 Samuel","chapter":18,"startVerse":4,"endVerse":4,"speaker":"David"},
    {"book":"2 Samuel","chapter":18,"startVerse":5,"endVerse":5,"speaker":"David"},
    {"book":"2 Samuel","chapter":18,"startVerse":11,"endVerse":11,"speaker":"Joab"},
    {"book":"2 Samuel","chapter":18,"startVerse":12,"endVerse":13,"speaker":"Joab"},
    {"book":"2 Samuel","chapter":18,"startVerse":14,"endVerse":14,"speaker":"Joab"},
    {"book":"2 Samuel","chapter":18,"startVerse":19,"endVerse":19,"speaker":"Ahimaaz"},
    {"book":"2 Samuel","chapter":18,"startVerse":20,"endVerse":20,"speaker":"Joab"},
    {"book":"2 Samuel","chapter":18,"startVerse":22,"endVerse":22,"speaker":"Ahimaaz"},
    {"book":"2 Samuel","chapter":18,"startVerse":22,"endVerse":22,"speaker":"Joab"},
    {"book":"2 Samuel","chapter":18,"startVerse":23,"endVerse":23,"speaker":"Ahimaaz"},
    {"book":"2 Samuel","chapter":18,"startVerse":25,"endVerse":25,"speaker":"David"},
    {"book":"2 Samuel","chapter":18,"startVerse":28,"endVerse":28,"speaker":"Ahimaaz"},
    {"book":"2 Samuel","chapter":18,"startVerse":29,"endVerse":29,"speaker":"David"},
    {"book":"2 Samuel","chapter":18,"startVerse":29,"endVerse":29,"speaker":"Ahimaaz"},
    {"book":"2 Samuel","chapter":18,"startVerse":31,"endVerse":31,"speaker":"Cushi"},
    {"book":"2 Samuel","chapter":18,"startVerse":32,"endVerse":32,"speaker":"David"},
    {"book":"2 Samuel","chapter":18,"startVerse":32,"endVerse":32,"speaker":"Cushi"},
    {"book":"2 Samuel","chapter":18,"startVerse":33,"endVerse":33,"speaker":"David"},
    {"book":"2 Samuel","chapter":19,"startVerse":1,"endVerse":2,"speaker":"Joab"},
    {"book":"2 Samuel","chapter":19,"startVerse":5,"endVerse":7,"speaker":"Joab"},
    {"book":"2 Samuel","chapter":19,"startVerse":19,"endVerse":20,"speaker":"Shimei"},
    {"book":"2 Samuel","chapter":19,"startVerse":21,"endVerse":21,"speaker":"Abishai"},
    {"book":"2 Samuel","chapter":19,"startVerse":22,"endVerse":23,"speaker":"David"},
    {"book":"2 Samuel","chapter":19,"startVerse":24,"endVerse":24,"speaker":"David"},
    {"book":"2 Samuel","chapter":19,"startVerse":26,"endVerse":28,"speaker":"Mephibosheth"},
    {"book":"2 Samuel","chapter":19,"startVerse":29,"endVerse":29,"speaker":"David"},
    {"book":"2 Samuel","chapter":19,"startVerse":30,"endVerse":30,"speaker":"Mephibosheth"},
    {"book":"2 Samuel","chapter":19,"startVerse":33,"endVerse":33,"speaker":"David"},
    {"book":"2 Samuel","chapter":19,"startVerse":34,"endVerse":37,"speaker":"Barzillai"},
    {"book":"2 Samuel","chapter":19,"startVerse":38,"endVerse":39,"speaker":"David"},
    {"book":"2 Samuel","chapter":20,"startVerse":1,"endVerse":1,"speaker":"Sheba"},
    {"book":"2 Samuel","chapter":20,"startVerse":4,"endVerse":4,"speaker":"David"},
    {"book":"2 Samuel","chapter":20,"startVerse":6,"endVerse":6,"speaker":"David"},
    {"book":"2 Samuel","chapter":20,"startVerse":9,"endVerse":9,"speaker":"Joab"},
    {"book":"2 Samuel","chapter":20,"startVerse":11,"endVerse":11,"speaker":"Joab"},
    {"book":"2 Samuel","chapter":21,"startVerse":1,"endVerse":1,"speaker":"Jesus Christ"},
    {"book":"2 Samuel","chapter":21,"startVerse":3,"endVerse":3,"speaker":"David"},
    {"book":"2 Samuel","chapter":21,"startVerse":4,"endVerse":4,"speaker":"David"},
    {"book":"2 Samuel","chapter":21,"startVerse":6,"endVerse":6,"speaker":"David"},
    {"book":"2 Samuel","chapter":22,"startVerse":2,"endVerse":51,"speaker":"David"},
    {"book":"2 Samuel","chapter":23,"startVerse":1,"endVerse":7,"speaker":"David"},
    {"book":"2 Samuel","chapter":24,"startVerse":2,"endVerse":2,"speaker":"David"},
    {"book":"2 Samuel","chapter":24,"startVerse":3,"endVerse":3,"speaker":"Joab"},
    {"book":"2 Samuel","chapter":24,"startVerse":10,"endVerse":10,"speaker":"David"},
    {"book":"2 Samuel","chapter":24,"startVerse":12,"endVerse":13,"speaker":"Gad"},
    {"book":"2 Samuel","chapter":24,"startVerse":14,"endVerse":14,"speaker":"David"},
    {"book":"2 Samuel","chapter":24,"startVerse":16,"endVerse":16,"speaker":"Jesus Christ"},
    {"book":"2 Samuel","chapter":24,"startVerse":17,"endVerse":17,"speaker":"David"},
    {"book":"2 Samuel","chapter":24,"startVerse":18,"endVerse":18,"speaker":"Gad"},
    {"book":"2 Samuel","chapter":24,"startVerse":21,"endVerse":21,"speaker":"Araunah"},
    {"book":"2 Samuel","chapter":24,"startVerse":22,"endVerse":22,"speaker":"Araunah"},
    {"book":"2 Samuel","chapter":24,"startVerse":23,"endVerse":23,"speaker":"Araunah"},
    {"book":"2 Samuel","chapter":24,"startVerse":24,"endVerse":24,"speaker":"David"}
  ],
  "missingCharacters": [],
  "summaries": [
    {"book":"2 Samuel","chapter":1,"summary":"David learns of Saul and Jonathan's deaths, executes the Amalekite messenger, and composes a lament for the fallen."},
    {"book":"2 Samuel","chapter":2,"summary":"David is anointed king of Judah at Hebron while Ish-bosheth rules Israel; civil war begins with the battle at Gibeon where Asahel is killed."},
    {"book":"2 Samuel","chapter":3,"summary":"Abner defects from Ish-bosheth to David but is killed by Joab; David publicly mourns Abner to prove his innocence."},
    {"book":"2 Samuel","chapter":4,"summary":"Ish-bosheth is assassinated by Rechab and Baanah; David executes them for murdering an innocent man."},
    {"book":"2 Samuel","chapter":5,"summary":"All Israel anoints David king at Hebron; he captures Jerusalem as his capital and defeats the Philistines twice with divine direction."},
    {"book":"2 Samuel","chapter":6,"summary":"David brings the Ark to Jerusalem with celebration; Uzzah is struck dead for touching it, and Michal despises David for dancing."},
    {"book":"2 Samuel","chapter":7,"summary":"David desires to build a temple, but God through Nathan establishes the Davidic Covenant, promising an everlasting throne; David prays in humility."},
    {"book":"2 Samuel","chapter":8,"summary":"David defeats the Philistines, Moabites, Syrians, and Edomites, expanding his kingdom and dedicating the spoils to the Lord."},
    {"book":"2 Samuel","chapter":9,"summary":"David shows kindness to Mephibosheth, son of Jonathan, restoring Saul's lands and granting him a permanent place at the royal table."},
    {"book":"2 Samuel","chapter":10,"summary":"The Ammonites humiliate David's ambassadors; Joab and Abishai defeat the combined Ammonite-Syrian forces in battle."},
    {"book":"2 Samuel","chapter":11,"summary":"David commits adultery with Bathsheba, fails to cover his sin through Uriah, and arranges Uriah's death in battle."},
    {"book":"2 Samuel","chapter":12,"summary":"Nathan confronts David with the parable of the ewe lamb; David repents, the child dies, and Solomon is born to Bathsheba."},
    {"book":"2 Samuel","chapter":13,"summary":"Amnon violates his half-sister Tamar; Absalom waits two years then has Amnon killed at a feast and flees to Geshur."},
    {"book":"2 Samuel","chapter":14,"summary":"Joab uses the wise woman of Tekoa to persuade David to recall Absalom from exile, though Absalom remains barred from the king's presence."},
    {"book":"2 Samuel","chapter":15,"summary":"Absalom conspires to steal the kingdom through four years of political manipulation; David flees Jerusalem weeping over the Mount of Olives."},
    {"book":"2 Samuel","chapter":16,"summary":"Ziba brings provisions and slanders Mephibosheth; Shimei curses David; Absalom enters Jerusalem and follows Ahithophel's counsel."},
    {"book":"2 Samuel","chapter":17,"summary":"Hushai defeats Ahithophel's counsel to attack David immediately; Ahithophel hangs himself and David escapes across the Jordan."},
    {"book":"2 Samuel","chapter":18,"summary":"David's forces defeat Absalom's army in the forest of Ephraim; Joab kills Absalom, and David mourns bitterly for his son."},
    {"book":"2 Samuel","chapter":19,"summary":"Joab rebukes David's mourning; David returns to Jerusalem, pardons Shimei, and navigates disputes among Judah and Israel."},
    {"book":"2 Samuel","chapter":20,"summary":"Sheba leads a revolt against David; Joab pursues him, and the wise woman of Abel delivers Sheba's head to end the rebellion."},
    {"book":"2 Samuel","chapter":21,"summary":"A three-year famine is traced to Saul's bloodguilt against the Gibeonites; David delivers Saul's descendants, and wars with Philistine giants follow."},
    {"book":"2 Samuel","chapter":22,"summary":"David's great psalm of deliverance, praising God as his rock, fortress, and shield who delivered him from all his enemies."},
    {"book":"2 Samuel","chapter":23,"summary":"David's last prophetic words and the catalog of his mighty men with their legendary feats of valor and loyalty."},
    {"book":"2 Samuel","chapter":24,"summary":"David numbers the people against Joab's counsel; God sends a plague as judgment, and David purchases Araunah's threshingfloor to build an altar."}
  ],
  "themes": [
    {"book":"2 Samuel","chapter":1,"themes":["grief","loyalty","honor","lament"]},
    {"book":"2 Samuel","chapter":2,"themes":["civil war","anointing","division","loyalty"]},
    {"book":"2 Samuel","chapter":3,"themes":["betrayal","murder","mourning","political alliance"]},
    {"book":"2 Samuel","chapter":4,"themes":["assassination","justice","accountability"]},
    {"book":"2 Samuel","chapter":5,"themes":["kingship","divine guidance","unity","conquest"]},
    {"book":"2 Samuel","chapter":6,"themes":["worship","reverence","holiness","celebration"]},
    {"book":"2 Samuel","chapter":7,"themes":["covenant","eternal promises","humility","prophecy"]},
    {"book":"2 Samuel","chapter":8,"themes":["conquest","sovereignty","dedication","divine protection"]},
    {"book":"2 Samuel","chapter":9,"themes":["covenant loyalty","mercy","kindness","grace"]},
    {"book":"2 Samuel","chapter":10,"themes":["honor","warfare","diplomacy","judgment"]},
    {"book":"2 Samuel","chapter":11,"themes":["temptation","adultery","deception","moral failure"]},
    {"book":"2 Samuel","chapter":12,"themes":["repentance","prophetic rebuke","consequences","mercy"]},
    {"book":"2 Samuel","chapter":13,"themes":["violence","revenge","family dysfunction","justice delayed"]},
    {"book":"2 Samuel","chapter":14,"themes":["exile","reconciliation","manipulation","wisdom"]},
    {"book":"2 Samuel","chapter":15,"themes":["rebellion","betrayal","flight","humility"]},
    {"book":"2 Samuel","chapter":16,"themes":["slander","cursing","deception","counsel"]},
    {"book":"2 Samuel","chapter":17,"themes":["counsel","espionage","providence","suicide"]},
    {"book":"2 Samuel","chapter":18,"themes":["battle","death","grief","disobedience"]},
    {"book":"2 Samuel","chapter":19,"themes":["restoration","mercy","reconciliation","political tension"]},
    {"book":"2 Samuel","chapter":20,"themes":["rebellion","loyalty","wisdom","swift justice"]},
    {"book":"2 Samuel","chapter":21,"themes":["bloodguilt","atonement","famine","justice"]},
    {"book":"2 Samuel","chapter":22,"themes":["deliverance","praise","divine power","thanksgiving"]},
    {"book":"2 Samuel","chapter":23,"themes":["last words","valor","mighty men","faithfulness"]},
    {"book":"2 Samuel","chapter":24,"themes":["pride","plague","repentance","sacrifice"]}
  ],
  "crossReferences": [
    {"book":"2 Samuel","chapter":1,"verse":18,"crossReference":"Joshua 10:13","type":"allusion","note":"References the book of Jasher, also cited in Joshua's account of the sun standing still."},
    {"book":"2 Samuel","chapter":5,"verse":2,"crossReference":"1 Chronicles 11:2","type":"parallel","note":"The anointing of David as shepherd and captain over Israel is recorded in both accounts."},
    {"book":"2 Samuel","chapter":7,"verse":12,"crossReference":"Acts 2:30","type":"fulfillment","note":"Peter cites this Davidic covenant promise as fulfilled in the resurrection of Christ."},
    {"book":"2 Samuel","chapter":7,"verse":14,"crossReference":"Hebrews 1:5","type":"quotation","note":"Quoted in the New Testament regarding the divine Sonship of Christ."},
    {"book":"2 Samuel","chapter":11,"verse":4,"crossReference":"Matthew 1:6","type":"allusion","note":"Matthew's genealogy of Jesus deliberately mentions Bathsheba as 'her that had been the wife of Uriah.'"},
    {"book":"2 Samuel","chapter":12,"verse":13,"crossReference":"Psalm 51:1","type":"parallel","note":"Psalm 51 is David's penitential psalm composed after Nathan's confrontation."},
    {"book":"2 Samuel","chapter":22,"verse":2,"crossReference":"Psalm 18:2","type":"parallel","note":"This psalm is virtually identical to Psalm 18, David's song of deliverance."},
    {"book":"2 Samuel","chapter":23,"verse":2,"crossReference":"2 Peter 1:21","type":"parallel","note":"David testifies the Spirit of the Lord spoke by him, illustrating how holy men spoke as moved by the Holy Ghost."},
    {"book":"2 Samuel","chapter":24,"verse":24,"crossReference":"1 Chronicles 21:24","type":"parallel","note":"David's refusal to offer burnt offerings without cost is recorded in both accounts."}
  ],
  "doctrinalTopics": [
    {"book":"2 Samuel","chapter":1,"topics":["mourning","honor","loyalty"]},
    {"book":"2 Samuel","chapter":2,"topics":["anointing","revelation","warfare"]},
    {"book":"2 Samuel","chapter":3,"topics":["justice","mourning","leadership"]},
    {"book":"2 Samuel","chapter":4,"topics":["justice","accountability"]},
    {"book":"2 Samuel","chapter":5,"topics":["kingship","revelation","covenant"]},
    {"book":"2 Samuel","chapter":6,"topics":["reverence","worship","holiness"]},
    {"book":"2 Samuel","chapter":7,"topics":["covenant","prophecy","humility","temple"]},
    {"book":"2 Samuel","chapter":8,"topics":["consecration","sovereignty","justice"]},
    {"book":"2 Samuel","chapter":9,"topics":["covenant","mercy","charity"]},
    {"book":"2 Samuel","chapter":10,"topics":["honor","judgment","warfare"]},
    {"book":"2 Samuel","chapter":11,"topics":["temptation","sin","accountability"]},
    {"book":"2 Samuel","chapter":12,"topics":["repentance","prophetic authority","mercy","consequences"]},
    {"book":"2 Samuel","chapter":13,"topics":["justice","sin","consequences"]},
    {"book":"2 Samuel","chapter":14,"topics":["reconciliation","wisdom","mercy"]},
    {"book":"2 Samuel","chapter":15,"topics":["humility","trust in God","rebellion"]},
    {"book":"2 Samuel","chapter":16,"topics":["patience","faith","counsel"]},
    {"book":"2 Samuel","chapter":17,"topics":["providence","counsel","faith"]},
    {"book":"2 Samuel","chapter":18,"topics":["consequences","obedience","grief"]},
    {"book":"2 Samuel","chapter":19,"topics":["forgiveness","restoration","mercy"]},
    {"book":"2 Samuel","chapter":20,"topics":["loyalty","wisdom","leadership"]},
    {"book":"2 Samuel","chapter":21,"topics":["atonement","justice","covenant"]},
    {"book":"2 Samuel","chapter":22,"topics":["praise","deliverance","faith","salvation"]},
    {"book":"2 Samuel","chapter":23,"topics":["prophecy","valor","faithfulness"]},
    {"book":"2 Samuel","chapter":24,"topics":["repentance","sacrifice","mercy","atonement"]}
  ],
  "historicalContext": [
    {"book":"2 Samuel","chapter":1,"era":"United Monarchy","approxDate":"c. 1010 BC","setting":"Ziklag"},
    {"book":"2 Samuel","chapter":2,"era":"United Monarchy","approxDate":"c. 1010 BC","setting":"Hebron and Gibeon"},
    {"book":"2 Samuel","chapter":3,"era":"United Monarchy","approxDate":"c. 1008 BC","setting":"Hebron"},
    {"book":"2 Samuel","chapter":4,"era":"United Monarchy","approxDate":"c. 1005 BC","setting":"Mahanaim"},
    {"book":"2 Samuel","chapter":5,"era":"United Monarchy","approxDate":"c. 1003 BC","setting":"Hebron and Jerusalem"},
    {"book":"2 Samuel","chapter":6,"era":"United Monarchy","approxDate":"c. 1000 BC","setting":"Jerusalem"},
    {"book":"2 Samuel","chapter":7,"era":"United Monarchy","approxDate":"c. 1000 BC","setting":"Jerusalem"},
    {"book":"2 Samuel","chapter":8,"era":"United Monarchy","approxDate":"c. 1000-990 BC","setting":"Syria, Moab, and Edom"},
    {"book":"2 Samuel","chapter":9,"era":"United Monarchy","approxDate":"c. 1000 BC","setting":"Jerusalem"},
    {"book":"2 Samuel","chapter":10,"era":"United Monarchy","approxDate":"c. 995 BC","setting":"Ammon and Syria"},
    {"book":"2 Samuel","chapter":11,"era":"United Monarchy","approxDate":"c. 993 BC","setting":"Jerusalem and Rabbah"},
    {"book":"2 Samuel","chapter":12,"era":"United Monarchy","approxDate":"c. 993 BC","setting":"Jerusalem"},
    {"book":"2 Samuel","chapter":13,"era":"United Monarchy","approxDate":"c. 990 BC","setting":"Jerusalem"},
    {"book":"2 Samuel","chapter":14,"era":"United Monarchy","approxDate":"c. 987 BC","setting":"Tekoa and Jerusalem"},
    {"book":"2 Samuel","chapter":15,"era":"United Monarchy","approxDate":"c. 983 BC","setting":"Jerusalem and Mount of Olives"},
    {"book":"2 Samuel","chapter":16,"era":"United Monarchy","approxDate":"c. 983 BC","setting":"Road from Jerusalem to the Jordan"},
    {"book":"2 Samuel","chapter":17,"era":"United Monarchy","approxDate":"c. 983 BC","setting":"Jerusalem and Mahanaim"},
    {"book":"2 Samuel","chapter":18,"era":"United Monarchy","approxDate":"c. 983 BC","setting":"Forest of Ephraim"},
    {"book":"2 Samuel","chapter":19,"era":"United Monarchy","approxDate":"c. 983 BC","setting":"Jordan River crossing and Jerusalem"},
    {"book":"2 Samuel","chapter":20,"era":"United Monarchy","approxDate":"c. 983 BC","setting":"Abel Beth-maachah"},
    {"book":"2 Samuel","chapter":21,"era":"United Monarchy","approxDate":"c. 980 BC","setting":"Gibeon and Philistia"},
    {"book":"2 Samuel","chapter":22,"era":"United Monarchy","approxDate":"c. 975 BC","setting":"Jerusalem"},
    {"book":"2 Samuel","chapter":23,"era":"United Monarchy","approxDate":"c. 970 BC","setting":"Jerusalem"},
    {"book":"2 Samuel","chapter":24,"era":"United Monarchy","approxDate":"c. 975 BC","setting":"Jerusalem, Araunah's threshingfloor"}
  ],
  "literaryGenres": [
    {"book":"2 Samuel","chapter":1,"genre":"narrative","subgenre":"lament"},
    {"book":"2 Samuel","chapter":2,"genre":"narrative","subgenre":"military record"},
    {"book":"2 Samuel","chapter":3,"genre":"narrative"},
    {"book":"2 Samuel","chapter":4,"genre":"narrative"},
    {"book":"2 Samuel","chapter":5,"genre":"narrative"},
    {"book":"2 Samuel","chapter":6,"genre":"narrative"},
    {"book":"2 Samuel","chapter":7,"genre":"narrative","subgenre":"prophecy"},
    {"book":"2 Samuel","chapter":8,"genre":"narrative","subgenre":"military record"},
    {"book":"2 Samuel","chapter":9,"genre":"narrative"},
    {"book":"2 Samuel","chapter":10,"genre":"narrative","subgenre":"military record"},
    {"book":"2 Samuel","chapter":11,"genre":"narrative"},
    {"book":"2 Samuel","chapter":12,"genre":"narrative","subgenre":"parable"},
    {"book":"2 Samuel","chapter":13,"genre":"narrative"},
    {"book":"2 Samuel","chapter":14,"genre":"narrative"},
    {"book":"2 Samuel","chapter":15,"genre":"narrative"},
    {"book":"2 Samuel","chapter":16,"genre":"narrative"},
    {"book":"2 Samuel","chapter":17,"genre":"narrative"},
    {"book":"2 Samuel","chapter":18,"genre":"narrative"},
    {"book":"2 Samuel","chapter":19,"genre":"narrative"},
    {"book":"2 Samuel","chapter":20,"genre":"narrative"},
    {"book":"2 Samuel","chapter":21,"genre":"narrative"},
    {"book":"2 Samuel","chapter":22,"genre":"narrative","subgenre":"psalm"},
    {"book":"2 Samuel","chapter":23,"genre":"narrative","subgenre":"prophecy"},
    {"book":"2 Samuel","chapter":24,"genre":"narrative"}
  ],
  "notableVerses": [
    {"book":"2 Samuel","chapter":1,"verses":[{"verse":19,"reason":"Beginning of David's lament: 'The beauty of Israel is slain upon thy high places.'"},{"verse":26,"reason":"David's tribute to Jonathan: 'Thy love to me was wonderful, passing the love of women.'"}]},
    {"book":"2 Samuel","chapter":2,"verses":[]},
    {"book":"2 Samuel","chapter":3,"verses":[{"verse":38,"reason":"David declares 'a prince and a great man is fallen this day in Israel' regarding Abner."}]},
    {"book":"2 Samuel","chapter":4,"verses":[]},
    {"book":"2 Samuel","chapter":5,"verses":[{"verse":10,"reason":"David went on, and grew great, and the LORD God of hosts was with him."}]},
    {"book":"2 Samuel","chapter":6,"verses":[{"verse":14,"reason":"David dances before the LORD with all his might—iconic image of exuberant worship."}]},
    {"book":"2 Samuel","chapter":7,"verses":[{"verse":12,"reason":"Promise that God will establish the seed after David and his kingdom forever."},{"verse":22,"reason":"David's prayer: 'There is none like thee, neither is there any God beside thee.'"}]},
    {"book":"2 Samuel","chapter":8,"verses":[]},
    {"book":"2 Samuel","chapter":9,"verses":[{"verse":7,"reason":"David shows kindness for Jonathan's sake—a model of covenant loyalty."}]},
    {"book":"2 Samuel","chapter":10,"verses":[]},
    {"book":"2 Samuel","chapter":11,"verses":[{"verse":27,"reason":"The turning point: 'the thing that David had done displeased the LORD.'"}]},
    {"book":"2 Samuel","chapter":12,"verses":[{"verse":7,"reason":"Nathan's confrontation: 'Thou art the man'—one of scripture's most dramatic moments."},{"verse":13,"reason":"David's immediate confession: 'I have sinned against the LORD.'"}]},
    {"book":"2 Samuel","chapter":13,"verses":[]},
    {"book":"2 Samuel","chapter":14,"verses":[{"verse":14,"reason":"The metaphor of spilt water: 'Neither doth God respect any person: yet doth he devise means, that his banished be not expelled from him.'"}]},
    {"book":"2 Samuel","chapter":15,"verses":[{"verse":26,"reason":"David's submission: 'Let him do to me as seemeth good unto him.'"}]},
    {"book":"2 Samuel","chapter":16,"verses":[]},
    {"book":"2 Samuel","chapter":17,"verses":[]},
    {"book":"2 Samuel","chapter":18,"verses":[{"verse":33,"reason":"David's anguished cry: 'O my son Absalom, my son, my son Absalom!'"}]},
    {"book":"2 Samuel","chapter":19,"verses":[]},
    {"book":"2 Samuel","chapter":20,"verses":[]},
    {"book":"2 Samuel","chapter":21,"verses":[]},
    {"book":"2 Samuel","chapter":22,"verses":[{"verse":2,"reason":"'The LORD is my rock, and my fortress, and my deliverer'—foundational declaration of trust."},{"verse":31,"reason":"'As for God, his way is perfect; the word of the LORD is tried.'"}]},
    {"book":"2 Samuel","chapter":23,"verses":[{"verse":2,"reason":"David's last words: 'The Spirit of the LORD spake by me, and his word was in my tongue.'"},{"verse":5,"reason":"David affirms God has made an everlasting covenant with him, ordered in all things."}]},
    {"book":"2 Samuel","chapter":24,"verses":[{"verse":14,"reason":"David chooses to fall into God's hands: 'Let us fall now into the hand of the LORD; for his mercies are great.'"},{"verse":24,"reason":"David refuses free offerings: 'Neither will I offer burnt offerings unto the LORD my God of that which doth cost me nothing.'"}]}
  ]
}